pycobb/__init__.py
pycobb/cli.py
pycobb/utils/__init__.py
pycobb-0.0.4.dist-info/LICENSE
pycobb-0.0.4.dist-info/METADATA
pycobb-0.0.4.dist-info/WHEEL
pycobb-0.0.4.dist-info/entry_points.txt
pycobb-0.0.4.dist-info/top_level.txt
pycobb-0.0.4.dist-info/RECORD
