Metadata-Version: 2.1
Name: pycobb
Version: 0.0.4
Summary: UNKNOWN
Home-page: https://github.com/ryan-byrne/pycobb
Author: Ryan Byrne
Author-email: ryan@byrne.es
License: MIT
Project-URL: Documentation, https://pycobb.readthedocs.io/en/latest/
Project-URL: Bug Reports, https://github.com/ryan-byrne/pycobb/issues
Keywords: baseball savant sabermetrics pycobb
Platform: UNKNOWN
Classifier: Programming Language :: Python :: 3
Classifier: License :: OSI Approved :: MIT License
Classifier: Operating System :: Microsoft :: Windows
Classifier: Operating System :: Microsoft :: Windows
Classifier: Development Status :: 4 - Beta
Requires-Python: >3.5
Requires-Dist: pandas
Requires-Dist: requests
Requires-Dist: matplotlib
